MANIFEST.in
data.xlsx
model.json
setting.json
setup.py
startup.sh
stop.sh
test.py
test2.py
Snail_JueweiPotSchedule.egg-info/PKG-INFO
Snail_JueweiPotSchedule.egg-info/SOURCES.txt
Snail_JueweiPotSchedule.egg-info/dependency_links.txt
Snail_JueweiPotSchedule.egg-info/requires.txt
Snail_JueweiPotSchedule.egg-info/top_level.txt
data/schedule/DATA_20191006.json
data/schedule/DATA_20191006.xlsx
data/schedule/DATA_20191007.json
data/schedule/DATA_20191007.xlsx
data/schedule/DATA_20191008.json
data/schedule/DATA_20191008.xlsx
data/schedule/DATA_20191009.json
data/schedule/DATA_20191009.xlsx
snailwebs/__init__.py
snailwebs/main.py
snailwebs/action/__init__.py
snailwebs/action/fileserver.py
snailwebs/api/__init__.py
snailwebs/api/schedule.py
snailwebs/common/__init__.py
snailwebs/common/schedule/__init__.py
snailwebs/common/schedule/model.py
snailwebs/common/schedule/pot.py
static/favicon.ico
static/index.html
static/template.html
static/css/app.css
static/css/index.css
static/css/template.css
static/fonts/iconfont.ttf
static/js/data.js
static/js/snail.common-es6-0.0.1.js
static/temp/Template-X1-YYYY-MM-DD.xlsx