Metadata-Version: 1.0
Name: Snail-JueweiPotSchedule
Version: 0.0.2
Summary: Juewei Pot Schedule
Home-page: UNKNOWN
Author: Snail
Author-email: snail_email@163.com
License: UNKNOWN
Keywords: snail,juewei,schedule
Platform: UNKNOWN
